hvc/__about__.py
hvc/__init__.py
hvc/audiofileIO.py
hvc/extract.py
hvc/koumura.py
hvc/metrics.py
hvc/parseconfig.py
hvc/predict.py
hvc/select.py
hvc/features/__init__.py
hvc/features/extract.py
hvc/features/feature_dicts.py
hvc/features/knn.py
hvc/features/neuralnet.py
hvc/features/tachibana.py
hvc/neuralnet/__init__.py
hvc/neuralnet/utils.py
hvc/neuralnet/models/__init__.py
hvc/neuralnet/models/dilated.py
hvc/neuralnet/models/flatwindow.py
hvc/neuralnet/models/models.py
hvc/neuralnet/models/naiveLSTM.py
hvc/parse/__init__.py
hvc/parse/extract.py
hvc/parse/feature_groups.yml
hvc/parse/features.yml
hvc/parse/predict.py
hvc/parse/ref_spect_params.py
hvc/parse/select.py
hvc/parse/utils.py
hvc/parse/validation.yml
hvc/plot/__init__.py
hvc/plot/plot.py
hvc/utils/__init__.py
hvc/utils/annotation.py
hvc/utils/datasets.py
hvc/utils/features.py
hvc/utils/general.py
hvc/utils/randomdotorg.py
hvc/utils/repos.yml
hybrid_vocal_classifier-0.3.1.dist-info/LICENSE
hybrid_vocal_classifier-0.3.1.dist-info/WHEEL
hybrid_vocal_classifier-0.3.1.dist-info/METADATA
hybrid_vocal_classifier-0.3.1.dist-info/RECORD
