Metadata-Version: 2.1
Name: hybrid-vocal-classifier
Version: 0.3.1
Summary: a Python machine learning library for animal vocalizations and bioacoustics
Author-email: David Nicholson <nickledave@users.noreply.github.com>
Requires-Python: >=3.7,<3.10
Classifier: License :: OSI Approved :: BSD License
Classifier: Development Status :: 5 - Production/Stable
Classifier: Programming Language :: Python
Classifier: Programming Language :: Python :: 3
Classifier: Programming Language :: Python :: 3.7
Classifier: Programming Language :: Python :: 3.8
Classifier: Programming Language :: Python :: 3.9
Classifier: Programming Language :: Python :: Implementation :: CPython
Requires-Dist: evfuncs>=0.3.2
Requires-Dist: numpy>=1.19.2
Requires-Dist: scipy>=1.6.2
Requires-Dist: matplotlib>=3.4.1
Requires-Dist: scikit-learn>=0.24.1
Requires-Dist: Keras>=2.4.3
Requires-Dist: tensorflow>=2.4.1
Requires-Dist: PyYAML>=5.4.1
Requires-Dist: joblib>=1.0.1
Requires-Dist: ipython>=7.22.0 ; extra == "dev"
Requires-Dist: black>=20.8b1 ; extra == "dev"
Requires-Dist: flit>=3.2 ; extra == "dev"
Requires-Dist: Sphinx>=3.5.3 ; extra == "doc"
Requires-Dist: numpydoc>=1.1.0 ; extra == "doc"
Requires-Dist: pytest>=6.2.3 ; extra == "test"
Requires-Dist: pytest-cov>=2.11.1 ; extra == "test"
Requires-Dist: coverage[toml]>=5.5 ; extra == "test"
Project-URL: Documentation, https://hybrid-vocal-classifier.readthedocs.io/en/latest/
Project-URL: Source, https://github.com/NickleDave/hybrid-vocal-classifier
Provides-Extra: dev
Provides-Extra: doc
Provides-Extra: test
